g42cloudsdkelb/__init__.py
g42cloudsdkelb/v3/__init__.py
g42cloudsdkelb/v3/elb_async_client.py
g42cloudsdkelb/v3/elb_client.py
g42cloudsdkelb/v3/model/__init__.py
g42cloudsdkelb/v3/model/api_version_info.py
g42cloudsdkelb/v3/model/autoscaling_ref.py
g42cloudsdkelb/v3/model/availability_zone.py
g42cloudsdkelb/v3/model/bandwidth_ref.py
g42cloudsdkelb/v3/model/batch_create_members_option.py
g42cloudsdkelb/v3/model/batch_create_members_request.py
g42cloudsdkelb/v3/model/batch_create_members_request_body.py
g42cloudsdkelb/v3/model/batch_create_members_response.py
g42cloudsdkelb/v3/model/batch_delete_ip_list_option.py
g42cloudsdkelb/v3/model/batch_delete_ip_list_request.py
g42cloudsdkelb/v3/model/batch_delete_ip_list_request_body.py
g42cloudsdkelb/v3/model/batch_delete_ip_list_response.py
g42cloudsdkelb/v3/model/batch_delete_members_option.py
g42cloudsdkelb/v3/model/batch_delete_members_request.py
g42cloudsdkelb/v3/model/batch_delete_members_request_body.py
g42cloudsdkelb/v3/model/batch_delete_members_response.py
g42cloudsdkelb/v3/model/batch_delete_members_state.py
g42cloudsdkelb/v3/model/batch_member.py
g42cloudsdkelb/v3/model/batch_update_policies_priority_request.py
g42cloudsdkelb/v3/model/batch_update_policies_priority_request_body.py
g42cloudsdkelb/v3/model/batch_update_policies_priority_response.py
g42cloudsdkelb/v3/model/batch_update_priority_request_body.py
g42cloudsdkelb/v3/model/certificate_info.py
g42cloudsdkelb/v3/model/change_loadbalancer_charge_mode_request.py
g42cloudsdkelb/v3/model/change_loadbalancer_charge_mode_request_body.py
g42cloudsdkelb/v3/model/change_loadbalancer_charge_mode_response.py
g42cloudsdkelb/v3/model/count_preoccupy_ip_num_request.py
g42cloudsdkelb/v3/model/count_preoccupy_ip_num_response.py
g42cloudsdkelb/v3/model/create_certificate_option.py
g42cloudsdkelb/v3/model/create_certificate_request.py
g42cloudsdkelb/v3/model/create_certificate_request_body.py
g42cloudsdkelb/v3/model/create_certificate_response.py
g42cloudsdkelb-0.0.10b0.dist-info/LICENSE
g42cloudsdkelb-0.0.10b0.dist-info/METADATA
g42cloudsdkelb-0.0.10b0.dist-info/WHEEL
g42cloudsdkelb-0.0.10b0.dist-info/top_level.txt
g42cloudsdkelb-0.0.10b0.dist-info/RECORD
